goat_adapters/langchain/__init__.py
goat_adapters/langchain/adapter.py
goat_sdk_adapter_langchain-0.1.1.dist-info/METADATA
goat_sdk_adapter_langchain-0.1.1.dist-info/WHEEL
goat_sdk_adapter_langchain-0.1.1.dist-info/RECORD
